ultrashort/__init__.py
ultrashort/array.py
ultrashort/double_quantum_wells.py
ultrashort/euclidean.py
ultrashort/fidelity.py
ultrashort/fourier.py
ultrashort/ode.py
ultrashort/param.py
ultrashort/plot.py
ultrashort/pulse.py
ultrashort/sinc.py
ultrashort/special.py
ultrashort/su2.py
ultrashort/su3.py
ultrashort/two_level_system.py
ultrashort/version.py
ultrashort/wigner.py
ultrashort-0.0.4.dist-info/LICENSE.txt
ultrashort-0.0.4.dist-info/METADATA
ultrashort-0.0.4.dist-info/WHEEL
ultrashort-0.0.4.dist-info/top_level.txt
ultrashort-0.0.4.dist-info/RECORD
